cabot_alert_typetalk/__init__.py
cabot_alert_typetalk/models.py
cabot_alert_typetalk/migrations/0001_initial.py
cabot_alert_typetalk/migrations/__init__.py
cabot_alert_typetalk-0.1.0.dist-info/LICENSE
cabot_alert_typetalk-0.1.0.dist-info/METADATA
cabot_alert_typetalk-0.1.0.dist-info/WHEEL
cabot_alert_typetalk-0.1.0.dist-info/top_level.txt
cabot_alert_typetalk-0.1.0.dist-info/RECORD
