Metadata-Version: 2.1
Name: cabot-alert-typetalk
Version: 0.1.0
Summary: UNKNOWN
Home-page: https://github.com/is2ei/cabot-alert-typetalk
Author: Issei Horie
Author-email: is2ei.horie@gmail.com
License: UNKNOWN
Project-URL: Bug Reports, https://github.com/is2ei/cabot-alert-typetalk/issues
Project-URL: Source, https://github.com/is2ei/cabot-alert-typetalk
Keywords: cabot alert typetalk
Platform: UNKNOWN
Classifier: Development Status :: 3 - Alpha
Classifier: License :: OSI Approved :: MIT License
